{
  "study_name": "cluster_state_holographic_unified",
  "status": "COMPLETE",
  "objective": "Revise and rerun the unified holographic cluster-state study using only exclusive D+R+SQR and D+R+CPSQR families, with N_cav=12 default physical validation and active-subspace reporting.",
  "problem_class": [
    "OPT",
    "ANA"
  ],
  "loop_iteration": 1,
  "current_phase": "COMPLETE",
  "completed_tasks": [
    "Read applicable skills and loop configuration",
    "Audited existing unified study inputs and report scope",
    "Implemented corrected exclusive-family rerun pipeline",
    "Ran restricted-family synthesis and physical validation",
    "Regenerated corrected local figures and Wigner appendix",
    "Rewrote report, README, improvements log, and reproducibility notebook",
    "Compiled and validated final outputs"
  ],
  "pending_tasks": [],
  "key_results": {
    "best_preliminary_sqr_fidelity_n4": 0.9992873166118118,
    "best_final_sqr_fidelity_n12": 0.9996347038280087,
    "best_final_sqr_leakage_n12": 0.0007773497078904512,
    "best_structured_family": "D + R + SQR",
    "best_final_cpsqr_fidelity_n12": 0.9974916564874692,
    "best_final_cpsqr_leakage_n12": 0.005423136287888486,
    "best_final_cpsqr_active_levels_n12": [0, 1, 2, 3, 4, 5],
    "grape_best_duration_ns": 800,
    "grape_replay_fidelity_n12": 0.976047891029903,
    "grape_open_system_fidelity": 0.918704803974449
  },
  "blockers": []
}
